<?xml version="1.0" encoding="UTF-8"?>
<cesAna xmlns="http://www.xces.org/schema/2003" version="1.0.4">
   <struct type="s" from="24" to="34"/>
   <struct type="s" from="43" to="217">
      <feat name="id" value="p1s1"/>
   </struct>
   <struct type="s" from="218" to="595">
      <feat name="id" value="p1s2"/>
   </struct>
   <struct type="s" from="596" to="1096">
      <feat name="id" value="p1s3"/>
   </struct>
   <struct type="s" from="1097" to="1385">
      <feat name="id" value="p1s4"/>
   </struct>
   <struct type="s" from="1394" to="1558">
      <feat name="id" value="p2s1"/>
   </struct>
   <struct type="s" from="1559" to="1741">
      <feat name="id" value="p2s2"/>
   </struct>
   <struct type="s" from="1742" to="1959">
      <feat name="id" value="p2s3"/>
   </struct>
   <struct type="s" from="1968" to="2179">
      <feat name="id" value="p2s4"/>
   </struct>
   <struct type="s" from="2188" to="2745">
      <feat name="id" value="p3s1"/>
   </struct>
   <struct type="s" from="2746" to="2877">
      <feat name="id" value="p3s2"/>
   </struct>
   <struct type="s" from="2886" to="3079">
      <feat name="id" value="p4s1"/>
   </struct>
   <struct type="s" from="3080" to="3189">
      <feat name="id" value="p4s2"/>
   </struct>
   <struct type="s" from="3198" to="3409">
      <feat name="id" value="p4s3"/>
   </struct>
   <struct type="s" from="3410" to="3624">
      <feat name="id" value="p4s4"/>
   </struct>
   <struct type="s" from="3647" to="3654"/>
   <struct type="s" from="3674" to="3688"/>
   <struct type="s" from="3699" to="3868">
      <feat name="id" value="p5s1"/>
   </struct>
   <struct type="s" from="3869" to="4119">
      <feat name="id" value="p5s2"/>
   </struct>
   <struct type="s" from="4120" to="4287">
      <feat name="id" value="p5s3"/>
   </struct>
   <struct type="s" from="4288" to="4429">
      <feat name="id" value="p5s4"/>
   </struct>
   <struct type="s" from="4458" to="4539"/>
   <struct type="s" from="4550" to="4898">
      <feat name="id" value="p6s1"/>
   </struct>
   <struct type="s" from="4899" to="5098">
      <feat name="id" value="p6s2"/>
   </struct>
   <struct type="s" from="5099" to="5256">
      <feat name="id" value="p6s3"/>
   </struct>
   <struct type="s" from="5257" to="5425">
      <feat name="id" value="p6s4"/>
   </struct>
   <struct type="s" from="5426" to="5586">
      <feat name="id" value="p6s5"/>
   </struct>
   <struct type="s" from="5597" to="5745">
      <feat name="id" value="p7s1"/>
   </struct>
   <struct type="s" from="5746" to="5947">
      <feat name="id" value="p7s2"/>
   </struct>
   <struct type="s" from="5976" to="6043"/>
   <struct type="s" from="6054" to="6162">
      <feat name="id" value="p8s1"/>
   </struct>
   <struct type="s" from="6163" to="6413">
      <feat name="id" value="p8s2"/>
   </struct>
   <struct type="s" from="6414" to="6525">
      <feat name="id" value="p8s3"/>
   </struct>
   <struct type="s" from="6526" to="6649">
      <feat name="id" value="p8s4"/>
   </struct>
   <struct type="s" from="6650" to="6853">
      <feat name="id" value="p8s5"/>
   </struct>
   <struct type="s" from="6854" to="6987">
      <feat name="id" value="p8s6"/>
   </struct>
   <struct type="s" from="6998" to="7158">
      <feat name="id" value="p9s1"/>
   </struct>
   <struct type="s" from="7159" to="7214">
      <feat name="id" value="p9s2"/>
   </struct>
   <struct type="s" from="7214" to="7244">
      <feat name="id" value="p9s3"/>
   </struct>
   <struct type="s" from="7255" to="7684">
      <feat name="id" value="p9s4"/>
   </struct>
   <struct type="s" from="7695" to="7881">
      <feat name="id" value="p10s1"/>
   </struct>
   <struct type="s" from="7892" to="8186">
      <feat name="id" value="p10s2"/>
   </struct>
   <struct type="s" from="8187" to="8303">
      <feat name="id" value="p10s3"/>
   </struct>
   <struct type="s" from="8304" to="8422">
      <feat name="id" value="p10s4"/>
   </struct>
   <struct type="s" from="8451" to="8544"/>
   <struct type="s" from="8555" to="8847">
      <feat name="id" value="p11s1"/>
   </struct>
   <struct type="s" from="8848" to="8854">
      <feat name="id" value="p11s2"/>
   </struct>
   <struct type="s" from="8865" to="9099">
      <feat name="id" value="p11s3"/>
   </struct>
   <struct type="s" from="9100" to="9188">
      <feat name="id" value="p11s4"/>
   </struct>
   <struct type="s" from="9199" to="9296">
      <feat name="id" value="p12s1"/>
   </struct>
   <struct type="s" from="9297" to="9573">
      <feat name="id" value="p12s2"/>
   </struct>
   <struct type="s" from="9584" to="10252">
      <feat name="id" value="p13s1"/>
   </struct>
   <struct type="s" from="10253" to="10489">
      <feat name="id" value="p13s2"/>
   </struct>
   <struct type="s" from="10490" to="10577">
      <feat name="id" value="p13s3"/>
   </struct>
   <struct type="s" from="10606" to="10649"/>
   <struct type="s" from="10660" to="10747">
      <feat name="id" value="p14s1"/>
   </struct>
   <struct type="s" from="10748" to="10879">
      <feat name="id" value="p14s2"/>
   </struct>
   <struct type="s" from="10880" to="10991">
      <feat name="id" value="p14s3"/>
   </struct>
   <struct type="s" from="10992" to="11147">
      <feat name="id" value="p14s4"/>
   </struct>
   <struct type="s" from="11147" to="11319">
      <feat name="id" value="p14s5"/>
   </struct>
   <struct type="s" from="11320" to="11460">
      <feat name="id" value="p14s6"/>
   </struct>
   <struct type="s" from="11492" to="11502"/>
   <struct type="s" from="11522" to="11564"/>
   <struct type="s" from="11575" to="11797">
      <feat name="id" value="p15s1"/>
   </struct>
   <struct type="s" from="11798" to="11905">
      <feat name="id" value="p15s2"/>
   </struct>
   <struct type="s" from="11916" to="11987">
      <feat name="id" value="p16s1"/>
   </struct>
   <struct type="s" from="11988" to="12071">
      <feat name="id" value="p16s2"/>
   </struct>
   <struct type="s" from="12072" to="12207">
      <feat name="id" value="p16s3"/>
   </struct>
   <struct type="s" from="12208" to="12338">
      <feat name="id" value="p16s4"/>
   </struct>
   <struct type="s" from="12339" to="12592">
      <feat name="id" value="p16s5"/>
   </struct>
   <struct type="s" from="12593" to="12927">
      <feat name="id" value="p16s6"/>
   </struct>
   <struct type="s" from="12928" to="13117">
      <feat name="id" value="p16s7"/>
   </struct>
   <struct type="s" from="13118" to="13244">
      <feat name="id" value="p16s8"/>
   </struct>
   <struct type="s" from="13245" to="13454">
      <feat name="id" value="p16s9"/>
   </struct>
   <struct type="s" from="13455" to="13642">
      <feat name="id" value="p16s10"/>
   </struct>
   <struct type="s" from="13643" to="13762">
      <feat name="id" value="p16s11"/>
   </struct>
   <struct type="s" from="13773" to="13803">
      <feat name="id" value="p17s1"/>
   </struct>
   <struct type="s" from="13804" to="14061">
      <feat name="id" value="p17s2"/>
   </struct>
   <struct type="s" from="14062" to="14201">
      <feat name="id" value="p17s3"/>
   </struct>
   <struct type="s" from="14202" to="14391">
      <feat name="id" value="p17s4"/>
   </struct>
   <struct type="s" from="14392" to="14527">
      <feat name="id" value="p17s5"/>
   </struct>
   <struct type="s" from="14556" to="14589"/>
   <struct type="s" from="14600" to="14736">
      <feat name="id" value="p18s1"/>
   </struct>
   <struct type="s" from="14737" to="14951">
      <feat name="id" value="p18s2"/>
   </struct>
   <struct type="s" from="14952" to="15120">
      <feat name="id" value="p18s3"/>
   </struct>
   <struct type="s" from="15121" to="15470">
      <feat name="id" value="p18s4"/>
   </struct>
   <struct type="s" from="15471" to="15622">
      <feat name="id" value="p18s5"/>
   </struct>
   <struct type="s" from="15633" to="15789">
      <feat name="id" value="p19s1"/>
   </struct>
   <struct type="s" from="15790" to="15984">
      <feat name="id" value="p19s2"/>
   </struct>
   <struct type="s" from="15984" to="16086">
      <feat name="id" value="p19s3"/>
   </struct>
   <struct type="s" from="16087" to="16242">
      <feat name="id" value="p19s4"/>
   </struct>
   <struct type="s" from="16243" to="16420">
      <feat name="id" value="p19s5"/>
   </struct>
   <struct type="s" from="16420" to="16471">
      <feat name="id" value="p19s6"/>
   </struct>
   <struct type="s" from="16472" to="16739">
      <feat name="id" value="p19s7"/>
   </struct>
   <struct type="s" from="16740" to="16914">
      <feat name="id" value="p19s8"/>
   </struct>
   <struct type="s" from="16915" to="17279">
      <feat name="id" value="p19s9"/>
   </struct>
   <struct type="s" from="17280" to="17546">
      <feat name="id" value="p19s10"/>
   </struct>
   <struct type="s" from="17547" to="17700">
      <feat name="id" value="p19s11"/>
   </struct>
   <struct type="s" from="17701" to="17853">
      <feat name="id" value="p19s12"/>
   </struct>
   <struct type="s" from="17854" to="18121">
      <feat name="id" value="p19s13"/>
   </struct>
   <struct type="s" from="18132" to="18355">
      <feat name="id" value="p20s1"/>
   </struct>
   <struct type="s" from="18366" to="18657">
      <feat name="id" value="p20s2"/>
   </struct>
   <struct type="s" from="18658" to="18913">
      <feat name="id" value="p20s3"/>
   </struct>
   <struct type="s" from="18914" to="19139">
      <feat name="id" value="p20s4"/>
   </struct>
   <struct type="s" from="19168" to="19228"/>
   <struct type="s" from="19239" to="19464">
      <feat name="id" value="p21s1"/>
   </struct>
   <struct type="s" from="19465" to="19707">
      <feat name="id" value="p21s2"/>
   </struct>
   <struct type="s" from="19718" to="19954">
      <feat name="id" value="p22s1"/>
   </struct>
   <struct type="s" from="19965" to="20814">
      <feat name="id" value="p22s2"/>
   </struct>
   <struct type="s" from="20825" to="20880">
      <feat name="id" value="p22s3"/>
   </struct>
   <struct type="s" from="20891" to="21051">
      <feat name="id" value="p22s4"/>
   </struct>
   <struct type="s" from="21052" to="21286">
      <feat name="id" value="p22s5"/>
   </struct>
   <struct type="s" from="21287" to="21682">
      <feat name="id" value="p22s6"/>
   </struct>
   <struct type="s" from="21693" to="21970">
      <feat name="id" value="p23s1"/>
   </struct>
   <struct type="s" from="21971" to="22093">
      <feat name="id" value="p23s2"/>
   </struct>
   <struct type="s" from="22094" to="22494">
      <feat name="id" value="p23s3"/>
   </struct>
   <struct type="s" from="22505" to="22714">
      <feat name="id" value="p24s1"/>
   </struct>
   <struct type="s" from="22715" to="22851">
      <feat name="id" value="p24s2"/>
   </struct>
   <struct type="s" from="22852" to="22990">
      <feat name="id" value="p24s3"/>
   </struct>
   <struct type="s" from="22991" to="23175">
      <feat name="id" value="p24s4"/>
   </struct>
   <struct type="s" from="23176" to="23531">
      <feat name="id" value="p24s5"/>
   </struct>
   <struct type="s" from="23532" to="23706">
      <feat name="id" value="p24s6"/>
   </struct>
   <struct type="s" from="23717" to="23928">
      <feat name="id" value="p24s7"/>
   </struct>
   <struct type="s" from="23929" to="24187">
      <feat name="id" value="p24s8"/>
   </struct>
   <struct type="s" from="24198" to="24303">
      <feat name="id" value="p25s1"/>
   </struct>
   <struct type="s" from="24304" to="24488">
      <feat name="id" value="p25s2"/>
   </struct>
   <struct type="s" from="24489" to="25158">
      <feat name="id" value="p25s3"/>
   </struct>
   <struct type="s" from="25159" to="25172">
      <feat name="id" value="p25s4"/>
   </struct>
   <struct type="s" from="25173" to="25396">
      <feat name="id" value="p25s5"/>
   </struct>
   <struct type="s" from="25397" to="25589">
      <feat name="id" value="p25s6"/>
   </struct>
   <struct type="s" from="25590" to="25860">
      <feat name="id" value="p25s7"/>
   </struct>
   <struct type="s" from="25861" to="26110">
      <feat name="id" value="p25s8"/>
   </struct>
   <struct type="s" from="26121" to="26209">
      <feat name="id" value="p26s1"/>
   </struct>
   <struct type="s" from="26210" to="26696">
      <feat name="id" value="p26s2"/>
   </struct>
   <struct type="s" from="26697" to="26881">
      <feat name="id" value="p26s3"/>
   </struct>
   <struct type="s" from="26892" to="27369">
      <feat name="id" value="p27s1"/>
   </struct>
   <struct type="s" from="27370" to="27761">
      <feat name="id" value="p27s2"/>
   </struct>
   <struct type="s" from="27772" to="28053">
      <feat name="id" value="p28s1"/>
   </struct>
   <struct type="s" from="28054" to="29027">
      <feat name="id" value="p28s2"/>
   </struct>
   <struct type="s" from="29059" to="29070"/>
   <struct type="s" from="29079" to="29243">
      <feat name="id" value="p29s1"/>
   </struct>
   <struct type="s" from="29252" to="29459">
      <feat name="id" value="p30s1"/>
   </struct>
   <struct type="s" from="29468" to="29646">
      <feat name="id" value="p31s1"/>
   </struct>
   <struct type="s" from="29647" to="29821">
      <feat name="id" value="p31s2"/>
   </struct>
   <struct type="s" from="29830" to="30004">
      <feat name="id" value="p32s1"/>
   </struct>
   <struct type="s" from="30013" to="30099">
      <feat name="id" value="p32s2"/>
   </struct>
   <struct type="s" from="30100" to="30180">
      <feat name="id" value="p32s3"/>
   </struct>
   <struct type="s" from="30189" to="30369">
      <feat name="id" value="p33s1"/>
   </struct>
   <struct type="s" from="30378" to="30620">
      <feat name="id" value="p34s1"/>
   </struct>
   <struct type="s" from="30629" to="30879">
      <feat name="id" value="p34s2"/>
   </struct>
   <struct type="s" from="30888" to="31069">
      <feat name="id" value="p34s3"/>
   </struct>
   <struct type="s" from="31070" to="31270">
      <feat name="id" value="p34s4"/>
   </struct>
   <struct type="s" from="31279" to="31498">
      <feat name="id" value="p35s1"/>
   </struct>
   <struct type="s" from="31499" to="31634">
      <feat name="id" value="p35s2"/>
   </struct>
   <struct type="s" from="31635" to="31736">
      <feat name="id" value="p35s3"/>
   </struct>
   <struct type="s" from="31737" to="31935">
      <feat name="id" value="p35s4"/>
   </struct>
   <struct type="s" from="31958" to="31979"/>
   <struct type="s" from="31999" to="32056"/>
   <struct type="s" from="32067" to="32572">
      <feat name="id" value="p36s1"/>
   </struct>
   <struct type="s" from="32573" to="32949">
      <feat name="id" value="p36s2"/>
   </struct>
   <struct type="s" from="32950" to="33106">
      <feat name="id" value="p36s3"/>
   </struct>
   <struct type="s" from="33117" to="33230">
      <feat name="id" value="p36s4"/>
   </struct>
   <struct type="s" from="33241" to="33370">
      <feat name="id" value="p36s5"/>
   </struct>
   <struct type="s" from="33399" to="33434"/>
   <struct type="s" from="33445" to="33603">
      <feat name="id" value="p37s1"/>
   </struct>
   <struct type="s" from="33604" to="33736">
      <feat name="id" value="p37s2"/>
   </struct>
   <struct type="s" from="33737" to="34044">
      <feat name="id" value="p37s3"/>
   </struct>
   <struct type="s" from="34045" to="34144">
      <feat name="id" value="p37s4"/>
   </struct>
   <struct type="s" from="34145" to="34356">
      <feat name="id" value="p37s5"/>
   </struct>
   <struct type="s" from="34367" to="35040">
      <feat name="id" value="p38s1"/>
   </struct>
</cesAna>