<?xml version="1.0" encoding="UTF-8"?>
<cesAna xmlns="http://www.xces.org/schema/2003" version="1.0.4">
   <struct type="VG" from="67" to="81">
      <feat name="voice" value="active"/>
      <feat name="tense" value="PrePer"/>
      <feat name="type" value="FVG"/>
   </struct>
   <struct type="VG" from="184" to="191">
      <feat name="voice" value="active"/>
      <feat name="tense" value="SimPre"/>
      <feat name="type" value="FVG"/>
   </struct>
   <struct type="VG" from="246" to="253">
      <feat name="voice" value="active"/>
      <feat name="tense" value="Pre"/>
      <feat name="type" value="PART"/>
   </struct>
   <struct type="VG" from="299" to="305">
      <feat name="voice" value="active"/>
      <feat name="tense" value="Pre"/>
      <feat name="type" value="PART"/>
   </struct>
   <struct type="VG" from="387" to="389">
      <feat name="voice" value="active"/>
      <feat name="tense" value="SimPre"/>
      <feat name="type" value="FVG"/>
   </struct>
   <struct type="VG" from="399" to="408">
      <feat name="voice" value="active"/>
      <feat name="tense" value="Inf"/>
      <feat name="type" value="NFVG"/>
   </struct>
   <struct type="VG" from="468" to="470">
      <feat name="voice" value="active"/>
      <feat name="tense" value="SimPre"/>
      <feat name="type" value="FVG"/>
   </struct>
   <struct type="VG" from="483" to="499">
      <feat name="voice" value="passive"/>
      <feat name="tense" value="Inf"/>
      <feat name="type" value="NFVG"/>
   </struct>
   <struct type="VG" from="521" to="526">
      <feat name="voice" value="none"/>
      <feat name="tense" value="Pas"/>
      <feat name="type" value="PART"/>
   </struct>
   <struct type="VG" from="556" to="567">
      <feat name="voice" value="active"/>
      <feat name="tense" value="PrePer"/>
      <feat name="type" value="FVG"/>
   </struct>
   <struct type="VG" from="568" to="573">
      <feat name="voice" value="active"/>
      <feat name="tense" value="Inf"/>
      <feat name="type" value="NFVG"/>
   </struct>
   <struct type="VG" from="746" to="761">
      <feat name="voice" value="passive"/>
      <feat name="tense" value="SimPre"/>
      <feat name="type" value="FVG"/>
   </struct>
   <struct type="VG" from="762" to="771">
      <feat name="voice" value="active"/>
      <feat name="tense" value="Inf"/>
      <feat name="type" value="NFVG"/>
   </struct>
   <struct type="VG" from="928" to="930">
      <feat name="voice" value="active"/>
      <feat name="tense" value="SimPre"/>
      <feat name="type" value="FVG"/>
   </struct>
   <struct type="VG" from="995" to="1014">
      <feat name="type" value="FVG"/>
      <feat name="tense" value="SimPre"/>
      <feat name="voice" value="active"/>
      <feat name="neg" value="yes"/>
   </struct>
   <struct type="VG" from="1041" to="1048">
      <feat name="voice" value="active"/>
      <feat name="tense" value="SimPre"/>
      <feat name="type" value="FVG"/>
   </struct>
   <struct type="VG" from="1097" to="1100">
      <feat name="voice" value="active"/>
      <feat name="tense" value="SimPre"/>
      <feat name="type" value="FVG"/>
   </struct>
   <struct type="VG" from="1230" to="1250">
      <feat name="voice" value="passive"/>
      <feat name="tense" value="PrePer"/>
      <feat name="type" value="FVG"/>
   </struct>
   <struct type="VG" from="1274" to="1292">
      <feat name="voice" value="active"/>
      <feat name="tense" value="Inf"/>
      <feat name="type" value="NFVG"/>
   </struct>
   <struct type="VG" from="1498" to="1503">
      <feat name="voice" value="none"/>
      <feat name="tense" value="Pas"/>
      <feat name="type" value="PART"/>
   </struct>
   <struct type="VG" from="1559" to="1566">
      <feat name="voice" value="active"/>
      <feat name="tense" value="SimPre"/>
      <feat name="type" value="FVG"/>
   </struct>
   <struct type="VG" from="1719" to="1721">
      <feat name="voice" value="active"/>
      <feat name="tense" value="SimPre"/>
      <feat name="type" value="FVG"/>
   </struct>
   <struct type="VG" from="1798" to="1809">
      <feat name="voice" value="active"/>
      <feat name="tense" value="Inf"/>
      <feat name="type" value="NFVG"/>
   </struct>
   <struct type="VG" from="1923" to="1929">
      <feat name="voice" value="active"/>
      <feat name="tense" value="SimPre"/>
      <feat name="type" value="FVG"/>
   </struct>
   <struct type="VG" from="1943" to="1954">
      <feat name="voice" value="active"/>
      <feat name="tense" value="Pre"/>
      <feat name="type" value="PART"/>
   </struct>
   <struct type="VG" from="2009" to="2016">
      <feat name="voice" value="none"/>
      <feat name="tense" value="Pas"/>
      <feat name="type" value="PART"/>
   </struct>
   <struct type="VG" from="2033" to="2035">
      <feat name="voice" value="active"/>
      <feat name="tense" value="SimPre"/>
      <feat name="type" value="FVG"/>
   </struct>
   <struct type="VG" from="2042" to="2046">
      <feat name="voice" value="active"/>
      <feat name="tense" value="SimPre"/>
      <feat name="type" value="FVG"/>
   </struct>
   <struct type="VG" from="2084" to="2092">
      <feat name="voice" value="active"/>
      <feat name="tense" value="SimPre"/>
      <feat name="type" value="FVG"/>
   </struct>
   <struct type="VG" from="2124" to="2140">
      <feat name="voice" value="none"/>
      <feat name="tense" value="none"/>
      <feat name="type" value="MODAL"/>
   </struct>
   <struct type="VG" from="2154" to="2161">
      <feat name="voice" value="none"/>
      <feat name="tense" value="Pas"/>
      <feat name="type" value="PART"/>
   </struct>
   <struct type="VG" from="2214" to="2222">
      <feat name="voice" value="active"/>
      <feat name="tense" value="SimPre"/>
      <feat name="type" value="FVG"/>
   </struct>
   <struct type="VG" from="2272" to="2279">
      <feat name="voice" value="active"/>
      <feat name="tense" value="SimPre"/>
      <feat name="type" value="FVG"/>
   </struct>
   <struct type="VG" from="2306" to="2313">
      <feat name="voice" value="none"/>
      <feat name="tense" value="Pas"/>
      <feat name="type" value="PART"/>
   </struct>
   <struct type="VG" from="2337" to="2340">
      <feat name="voice" value="active"/>
      <feat name="tense" value="SimPre"/>
      <feat name="type" value="FVG"/>
   </struct>
   <struct type="VG" from="2372" to="2394">
      <feat name="voice" value="active"/>
      <feat name="tense" value="PreCon"/>
      <feat name="type" value="FVG"/>
   </struct>
   <struct type="VG" from="2504" to="2516">
      <feat name="voice" value="active"/>
      <feat name="tense" value="Pre"/>
      <feat name="type" value="PART"/>
   </struct>
   <struct type="VG" from="2556" to="2561">
      <feat name="voice" value="none"/>
      <feat name="tense" value="Pas"/>
      <feat name="type" value="PART"/>
   </struct>
   <struct type="VG" from="2623" to="2635">
      <feat name="voice" value="passive"/>
      <feat name="tense" value="SimPas"/>
      <feat name="type" value="FVG"/>
   </struct>
   <struct type="VG" from="2640" to="2651">
      <feat name="voice" value="none"/>
      <feat name="tense" value="Pas"/>
      <feat name="type" value="PART"/>
   </struct>
   <struct type="VG" from="2714" to="2736">
      <feat name="voice" value="passive"/>
      <feat name="tense" value="PrePer"/>
      <feat name="type" value="FVG"/>
   </struct>
   <struct type="VG" from="2909" to="2918">
      <feat name="voice" value="active"/>
      <feat name="tense" value="SimPre"/>
      <feat name="type" value="FVG"/>
   </struct>
   <struct type="VG" from="3067" to="3078">
      <feat name="voice" value="passive"/>
      <feat name="tense" value="SimPre"/>
      <feat name="type" value="FVG"/>
   </struct>
   <struct type="VG" from="3134" to="3136">
      <feat name="voice" value="active"/>
      <feat name="tense" value="SimPre"/>
      <feat name="type" value="FVG"/>
   </struct>
   <struct type="VG" from="3161" to="3186">
      <feat name="voice" value="none"/>
      <feat name="tense" value="Pre"/>
      <feat name="type" value="SPECIAL"/>
   </struct>
   <struct type="VG" from="3250" to="3256">
      <feat name="voice" value="passive"/>
      <feat name="tense" value="SimPre"/>
      <feat name="type" value="FVG"/>
   </struct>
   <struct type="VG" from="3291" to="3297">
      <feat name="voice" value="active"/>
      <feat name="tense" value="SimPre"/>
      <feat name="type" value="FVG"/>
   </struct>
   <struct type="VG" from="3340" to="3346">
      <feat name="voice" value="passive"/>
      <feat name="tense" value="SimPre"/>
      <feat name="type" value="FVG"/>
   </struct>
   <struct type="VG" from="3403" to="3430">
      <feat name="voice" value="passive"/>
      <feat name="tense" value="PrePer"/>
      <feat name="type" value="FVG"/>
   </struct>
   <struct type="VG" from="3491" to="3505">
      <feat name="voice" value="passive"/>
      <feat name="tense" value="SimPre"/>
      <feat name="type" value="FVG"/>
   </struct>
   <struct type="VG" from="3521" to="3525">
      <feat name="voice" value="active"/>
      <feat name="tense" value="SimPre"/>
      <feat name="type" value="FVG"/>
   </struct>
   <struct type="VG" from="3570" to="3572">
      <feat name="voice" value="active"/>
      <feat name="tense" value="SimPre"/>
      <feat name="type" value="FVG"/>
   </struct>
   <struct type="VG" from="3579" to="3583">
      <feat name="voice" value="active"/>
      <feat name="tense" value="SimPre"/>
      <feat name="type" value="FVG"/>
   </struct>
   <struct type="VG" from="3647" to="3655">
      <feat name="voice" value="active"/>
      <feat name="tense" value="SimPas"/>
      <feat name="type" value="FVG"/>
   </struct>
   <struct type="VG" from="3673" to="3680">
      <feat name="voice" value="active"/>
      <feat name="tense" value="SimPre"/>
      <feat name="type" value="FVG"/>
   </struct>
   <struct type="VG" from="3705" to="3714">
      <feat name="voice" value="active"/>
      <feat name="tense" value="Pre"/>
      <feat name="type" value="PART"/>
   </struct>
   <struct type="VG" from="3743" to="3748">
      <feat name="voice" value="none"/>
      <feat name="tense" value="Pas"/>
      <feat name="type" value="PART"/>
   </struct>
   <struct type="VG" from="3831" to="3836">
      <feat name="voice" value="active"/>
      <feat name="tense" value="SimPre"/>
      <feat name="type" value="FVG"/>
   </struct>
   <struct type="VG" from="3945" to="3956">
      <feat name="voice" value="active"/>
      <feat name="tense" value="SimPre"/>
      <feat name="type" value="FVG"/>
   </struct>
   <struct type="VG" from="4055" to="4062">
      <feat name="type" value="FVG"/>
      <feat name="tense" value="SimPre"/>
      <feat name="voice" value="active"/>
      <feat name="neg" value="yes"/>
   </struct>
   <struct type="VG" from="4094" to="4100">
      <feat name="voice" value="active"/>
      <feat name="tense" value="Inf"/>
      <feat name="type" value="NFVG"/>
   </struct>
   <struct type="VG" from="4101" to="4118">
      <feat name="voice" value="active"/>
      <feat name="tense" value="Inf"/>
      <feat name="type" value="NFVG"/>
   </struct>
   <struct type="VG" from="4258" to="4267">
      <feat name="voice" value="active"/>
      <feat name="tense" value="Pre"/>
      <feat name="type" value="PART"/>
   </struct>
   <struct type="VG" from="4324" to="4332">
      <feat name="voice" value="active"/>
      <feat name="tense" value="SimPre"/>
      <feat name="type" value="FVG"/>
   </struct>
   <struct type="VG" from="4345" to="4356">
      <feat name="voice" value="active"/>
      <feat name="tense" value="Pre"/>
      <feat name="type" value="PART"/>
   </struct>
   <struct type="VG" from="4420" to="4430">
      <feat name="voice" value="active"/>
      <feat name="tense" value="SimFut"/>
      <feat name="type" value="FVG"/>
   </struct>
   <struct type="VG" from="4474" to="4476">
      <feat name="voice" value="active"/>
      <feat name="tense" value="SimPre"/>
      <feat name="type" value="FVG"/>
   </struct>
   <struct type="VG" from="4496" to="4501">
      <feat name="voice" value="none"/>
      <feat name="tense" value="Pas"/>
      <feat name="type" value="PART"/>
   </struct>
   <struct type="VG" from="4532" to="4535">
      <feat name="voice" value="active"/>
      <feat name="tense" value="SimPre"/>
      <feat name="type" value="FVG"/>
   </struct>
   <struct type="VG" from="4555" to="4558">
      <feat name="voice" value="active"/>
      <feat name="tense" value="SimPre"/>
      <feat name="type" value="FVG"/>
   </struct>
   <struct type="VG" from="4678" to="4689">
      <feat name="voice" value="passive"/>
      <feat name="tense" value="SimPre"/>
      <feat name="type" value="FVG"/>
   </struct>
   <struct type="VG" from="4706" to="4712">
      <feat name="voice" value="active"/>
      <feat name="tense" value="SimPre"/>
      <feat name="type" value="FVG"/>
   </struct>
   <struct type="VG" from="4790" to="4792">
      <feat name="voice" value="active"/>
      <feat name="tense" value="SimPre"/>
      <feat name="type" value="FVG"/>
   </struct>
   <struct type="VG" from="4833" to="4835">
      <feat name="voice" value="active"/>
      <feat name="tense" value="SimPre"/>
      <feat name="type" value="FVG"/>
   </struct>
   <struct type="VG" from="4863" to="4866">
      <feat name="voice" value="active"/>
      <feat name="tense" value="SimPre"/>
      <feat name="type" value="FVG"/>
   </struct>
   <struct type="VG" from="4872" to="4883">
      <feat name="voice" value="none"/>
      <feat name="tense" value="Pas"/>
      <feat name="type" value="PART"/>
   </struct>
   <struct type="VG" from="4904" to="4913">
      <feat name="voice" value="active"/>
      <feat name="tense" value="Pre"/>
      <feat name="type" value="PART"/>
   </struct>
   <struct type="VG" from="5056" to="5068">
      <feat name="voice" value="passive"/>
      <feat name="tense" value="SimPre"/>
      <feat name="type" value="FVG"/>
   </struct>
   <struct type="VG" from="5264" to="5289">
      <feat name="type" value="FVG"/>
      <feat name="tense" value="SimPre"/>
      <feat name="voice" value="active"/>
      <feat name="neg" value="yes"/>
   </struct>
   <struct type="VG" from="5376" to="5378">
      <feat name="voice" value="active"/>
      <feat name="tense" value="SimPre"/>
      <feat name="type" value="FVG"/>
   </struct>
   <struct type="VG" from="5418" to="5424">
      <feat name="voice" value="active"/>
      <feat name="tense" value="SimPre"/>
      <feat name="type" value="FVG"/>
   </struct>
   <struct type="VG" from="5463" to="5473">
      <feat name="voice" value="active"/>
      <feat name="tense" value="Pre"/>
      <feat name="type" value="PART"/>
   </struct>
   <struct type="VG" from="5512" to="5519">
      <feat name="voice" value="active"/>
      <feat name="tense" value="Inf"/>
      <feat name="type" value="NFVG"/>
   </struct>
   <struct type="VG" from="5627" to="5641">
      <feat name="voice" value="none"/>
      <feat name="tense" value="Pre"/>
      <feat name="type" value="SPECIAL"/>
   </struct>
   <struct type="VG" from="5684" to="5686">
      <feat name="voice" value="active"/>
      <feat name="tense" value="SimPre"/>
      <feat name="type" value="FVG"/>
   </struct>
   <struct type="VG" from="5691" to="5697">
      <feat name="voice" value="active"/>
      <feat name="tense" value="SimPre"/>
      <feat name="type" value="FVG"/>
   </struct>
   <struct type="VG" from="5737" to="5747">
      <feat name="voice" value="active"/>
      <feat name="tense" value="Inf"/>
      <feat name="type" value="NFVG"/>
   </struct>
   <struct type="VG" from="5822" to="5834">
      <feat name="voice" value="passive"/>
      <feat name="tense" value="SimPre"/>
      <feat name="type" value="FVG"/>
   </struct>
   <struct type="VG" from="5932" to="5937">
      <feat name="voice" value="active"/>
      <feat name="tense" value="Inf"/>
      <feat name="type" value="NFVG"/>
   </struct>
   <struct type="VG" from="5952" to="5957">
      <feat name="voice" value="active"/>
      <feat name="tense" value="SimPre"/>
      <feat name="type" value="FVG"/>
   </struct>
   <struct type="VG" from="6015" to="6017">
      <feat name="voice" value="active"/>
      <feat name="tense" value="SimPre"/>
      <feat name="type" value="FVG"/>
   </struct>
   <struct type="VG" from="6059" to="6062">
      <feat name="voice" value="active"/>
      <feat name="tense" value="SimPre"/>
      <feat name="type" value="FVG"/>
   </struct>
   <struct type="VG" from="6212" to="6221">
      <feat name="voice" value="active"/>
      <feat name="tense" value="SimPre"/>
      <feat name="type" value="FVG"/>
   </struct>
   <struct type="VG" from="6304" to="6312">
      <feat name="voice" value="active"/>
      <feat name="tense" value="SimPre"/>
      <feat name="type" value="FVG"/>
   </struct>
   <struct type="VG" from="6352" to="6358">
      <feat name="voice" value="active"/>
      <feat name="tense" value="SimPre"/>
      <feat name="type" value="FVG"/>
   </struct>
   <struct type="VG" from="6438" to="6448">
      <feat name="voice" value="active"/>
      <feat name="tense" value="SimFut"/>
      <feat name="type" value="FVG"/>
   </struct>
   <struct type="VG" from="6651" to="6659">
      <feat name="voice" value="none"/>
      <feat name="tense" value="Pas"/>
      <feat name="type" value="PART"/>
   </struct>
   <struct type="VG" from="6691" to="6698">
      <feat name="voice" value="active"/>
      <feat name="tense" value="SimPas"/>
      <feat name="type" value="FVG"/>
   </struct>
   <struct type="VG" from="6717" to="6725">
      <feat name="voice" value="active"/>
      <feat name="tense" value="Pre"/>
      <feat name="type" value="PART"/>
   </struct>
   <struct type="VG" from="6772" to="6777">
      <feat name="voice" value="none"/>
      <feat name="tense" value="Pas"/>
      <feat name="type" value="PART"/>
   </struct>
   <struct type="VG" from="6791" to="6798">
      <feat name="voice" value="active"/>
      <feat name="tense" value="Pre"/>
      <feat name="type" value="PART"/>
   </struct>
   <struct type="VG" from="6983" to="6990">
      <feat name="voice" value="active"/>
      <feat name="tense" value="SimPre"/>
      <feat name="type" value="FVG"/>
   </struct>
   <struct type="VG" from="7030" to="7035">
      <feat name="voice" value="active"/>
      <feat name="tense" value="SimPre"/>
      <feat name="type" value="FVG"/>
   </struct>
   <struct type="VG" from="7086" to="7098">
      <feat name="voice" value="passive"/>
      <feat name="tense" value="SimPre"/>
      <feat name="type" value="FVG"/>
   </struct>
   <struct type="VG" from="7134" to="7147">
      <feat name="voice" value="passive"/>
      <feat name="tense" value="SimPre"/>
      <feat name="type" value="FVG"/>
   </struct>
   <struct type="VG" from="7151" to="7158">
      <feat name="voice" value="active"/>
      <feat name="tense" value="Pre"/>
      <feat name="type" value="PART"/>
   </struct>
   <struct type="VG" from="7164" to="7165">
      <feat name="voice" value="active"/>
      <feat name="tense" value="SimPre"/>
      <feat name="type" value="FVG"/>
   </struct>
   <struct type="VG" from="7181" to="7182">
      <feat name="voice" value="active"/>
      <feat name="tense" value="SimPre"/>
      <feat name="type" value="FVG"/>
   </struct>
   <struct type="VG" from="7206" to="7209">
      <feat name="voice" value="active"/>
      <feat name="tense" value="Inf"/>
      <feat name="type" value="NFVG"/>
   </struct>
   <struct type="VG" from="7275" to="7280">
      <feat name="voice" value="active"/>
      <feat name="tense" value="Pre"/>
      <feat name="type" value="PART"/>
   </struct>
   <struct type="VG" from="7318" to="7337">
      <feat name="voice" value="none"/>
      <feat name="tense" value="Pre"/>
      <feat name="type" value="SPECIAL"/>
   </struct>
   <struct type="VG" from="7355" to="7362">
      <feat name="voice" value="none"/>
      <feat name="tense" value="Pas"/>
      <feat name="type" value="PART"/>
   </struct>
   <struct type="VG" from="7387" to="7397">
      <feat name="voice" value="active"/>
      <feat name="tense" value="Pre"/>
      <feat name="type" value="PART"/>
   </struct>
   <struct type="VG" from="7504" to="7512">
      <feat name="voice" value="passive"/>
      <feat name="tense" value="SimPre"/>
      <feat name="type" value="FVG"/>
   </struct>
   <struct type="VG" from="7542" to="7547">
      <feat name="voice" value="active"/>
      <feat name="tense" value="Pre"/>
      <feat name="type" value="PART"/>
   </struct>
   <struct type="VG" from="7578" to="7593">
      <feat name="voice" value="none"/>
      <feat name="tense" value="none"/>
      <feat name="type" value="MODAL"/>
   </struct>
   <struct type="VG" from="7692" to="7697">
      <feat name="voice" value="active"/>
      <feat name="tense" value="SimPre"/>
      <feat name="type" value="FVG"/>
   </struct>
   <struct type="VG" from="7714" to="7734">
      <feat name="voice" value="none"/>
      <feat name="tense" value="Pre"/>
      <feat name="type" value="SPECIAL"/>
   </struct>
   <struct type="VG" from="7770" to="7780">
      <feat name="voice" value="passive"/>
      <feat name="tense" value="SimPre"/>
      <feat name="type" value="FVG"/>
   </struct>
   <struct type="VG" from="7896" to="7899">
      <feat name="voice" value="active"/>
      <feat name="tense" value="SimPre"/>
      <feat name="type" value="FVG"/>
   </struct>
   <struct type="VG" from="7945" to="7950">
      <feat name="voice" value="active"/>
      <feat name="tense" value="SimPre"/>
      <feat name="type" value="FVG"/>
   </struct>
   <struct type="VG" from="7969" to="7973">
      <feat name="voice" value="active"/>
      <feat name="tense" value="SimPre"/>
      <feat name="type" value="FVG"/>
   </struct>
   <struct type="VG" from="8036" to="8048">
      <feat name="voice" value="none"/>
      <feat name="tense" value="none"/>
      <feat name="type" value="MODAL"/>
   </struct>
   <struct type="VG" from="8085" to="8093">
      <feat name="voice" value="active"/>
      <feat name="tense" value="SimPre"/>
      <feat name="type" value="FVG"/>
   </struct>
   <struct type="VG" from="8104" to="8116">
      <feat name="voice" value="active"/>
      <feat name="tense" value="Inf"/>
      <feat name="type" value="NFVG"/>
   </struct>
   <struct type="VG" from="8216" to="8225">
      <feat name="voice" value="active"/>
      <feat name="tense" value="Pre"/>
      <feat name="type" value="PART"/>
   </struct>
   <struct type="VG" from="8238" to="8247">
      <feat name="voice" value="active"/>
      <feat name="tense" value="Inf"/>
      <feat name="type" value="NFVG"/>
   </struct>
   <struct type="VG" from="8343" to="8351">
      <feat name="voice" value="active"/>
      <feat name="tense" value="SimPre"/>
      <feat name="type" value="FVG"/>
   </struct>
   <struct type="VG" from="8518" to="8523">
      <feat name="voice" value="active"/>
      <feat name="tense" value="SimPre"/>
      <feat name="type" value="FVG"/>
   </struct>
   <struct type="VG" from="8585" to="8596">
      <feat name="type" value="FVG"/>
      <feat name="tense" value="SimPre"/>
      <feat name="voice" value="active"/>
      <feat name="neg" value="yes"/>
   </struct>
   <struct type="VG" from="8680" to="8689">
      <feat name="voice" value="passive"/>
      <feat name="tense" value="SimPre"/>
      <feat name="type" value="FVG"/>
   </struct>
   <struct type="VG" from="8869" to="8871">
      <feat name="voice" value="active"/>
      <feat name="tense" value="SimPre"/>
      <feat name="type" value="FVG"/>
   </struct>
   <struct type="VG" from="8939" to="8952">
      <feat name="voice" value="passive"/>
      <feat name="tense" value="SimPre"/>
      <feat name="type" value="FVG"/>
   </struct>
   <struct type="VG" from="8999" to="9007">
      <feat name="voice" value="active"/>
      <feat name="tense" value="Pre"/>
      <feat name="type" value="PART"/>
   </struct>
   <struct type="VG" from="9083" to="9091">
      <feat name="voice" value="active"/>
      <feat name="tense" value="PrePer"/>
      <feat name="type" value="FVG"/>
   </struct>
   <struct type="VG" from="9219" to="9221">
      <feat name="voice" value="active"/>
      <feat name="tense" value="SimPre"/>
      <feat name="type" value="FVG"/>
   </struct>
   <struct type="VG" from="9367" to="9378">
      <feat name="voice" value="active"/>
      <feat name="tense" value="Pre"/>
      <feat name="type" value="PART"/>
   </struct>
   <struct type="VG" from="9405" to="9407">
      <feat name="voice" value="active"/>
      <feat name="tense" value="SimPre"/>
      <feat name="type" value="FVG"/>
   </struct>
   <struct type="VG" from="9487" to="9504">
      <feat name="voice" value="passive"/>
      <feat name="tense" value="PrePer"/>
      <feat name="type" value="FVG"/>
   </struct>
   <struct type="VG" from="9688" to="9696">
      <feat name="voice" value="none"/>
      <feat name="tense" value="Pas"/>
      <feat name="type" value="PART"/>
   </struct>
   <struct type="VG" from="9750" to="9757">
      <feat name="voice" value="active"/>
      <feat name="tense" value="SimPre"/>
      <feat name="type" value="FVG"/>
   </struct>
   <struct type="VG" from="9904" to="9910">
      <feat name="voice" value="none"/>
      <feat name="tense" value="none"/>
      <feat name="type" value="MODAL"/>
   </struct>
   <struct type="VG" from="10042" to="10045">
      <feat name="voice" value="active"/>
      <feat name="tense" value="SimPre"/>
      <feat name="type" value="FVG"/>
   </struct>
   <struct type="VG" from="10062" to="10065">
      <feat name="voice" value="active"/>
      <feat name="tense" value="Inf"/>
      <feat name="type" value="NFVG"/>
   </struct>
   <struct type="VG" from="10076" to="10083">
      <feat name="voice" value="active"/>
      <feat name="tense" value="Pre"/>
      <feat name="type" value="PART"/>
   </struct>
   <struct type="VG" from="10102" to="10112">
      <feat name="voice" value="none"/>
      <feat name="tense" value="none"/>
      <feat name="type" value="MODAL"/>
   </struct>
   <struct type="VG" from="10125" to="10132">
      <feat name="voice" value="none"/>
      <feat name="tense" value="Pas"/>
      <feat name="type" value="PART"/>
   </struct>
   <struct type="VG" from="10243" to="10249">
      <feat name="voice" value="active"/>
      <feat name="tense" value="SimPre"/>
      <feat name="type" value="FVG"/>
   </struct>
   <struct type="VG" from="10374" to="10378">
      <feat name="voice" value="active"/>
      <feat name="tense" value="SimPre"/>
      <feat name="type" value="FVG"/>
   </struct>
   <struct type="VG" from="10379" to="10388">
      <feat name="voice" value="active"/>
      <feat name="tense" value="Inf"/>
      <feat name="type" value="NFVG"/>
   </struct>
   <struct type="VG" from="10457" to="10468">
      <feat name="voice" value="none"/>
      <feat name="tense" value="Pas"/>
      <feat name="type" value="PART"/>
   </struct>
   <struct type="VG" from="10518" to="10525">
      <feat name="voice" value="none"/>
      <feat name="tense" value="Pas"/>
      <feat name="type" value="PART"/>
   </struct>
   <struct type="VG" from="10700" to="10711">
      <feat name="voice" value="passive"/>
      <feat name="tense" value="Inf"/>
      <feat name="type" value="NFVG"/>
   </struct>
   <struct type="VG" from="10773" to="10783">
      <feat name="voice" value="none"/>
      <feat name="tense" value="none"/>
      <feat name="type" value="MODAL"/>
   </struct>
   <struct type="VG" from="10867" to="10878">
      <feat name="voice" value="active"/>
      <feat name="tense" value="SimPre"/>
      <feat name="type" value="FVG"/>
   </struct>
   <struct type="VG" from="10890" to="10897">
      <feat name="voice" value="none"/>
      <feat name="tense" value="Pas"/>
      <feat name="type" value="PART"/>
   </struct>
   <struct type="VG" from="10898" to="10907">
      <feat name="voice" value="active"/>
      <feat name="tense" value="SimPre"/>
      <feat name="type" value="FVG"/>
   </struct>
   <struct type="VG" from="10942" to="10944">
      <feat name="voice" value="active"/>
      <feat name="tense" value="SimPre"/>
      <feat name="type" value="FVG"/>
   </struct>
   <struct type="VG" from="11076" to="11081">
      <feat name="voice" value="active"/>
      <feat name="tense" value="SimPre"/>
      <feat name="type" value="FVG"/>
   </struct>
   <struct type="VG" from="11123" to="11132">
      <feat name="voice" value="passive"/>
      <feat name="tense" value="SimPre"/>
      <feat name="type" value="FVG"/>
   </struct>
   <struct type="VG" from="11160" to="11163">
      <feat name="voice" value="active"/>
      <feat name="tense" value="SimPre"/>
      <feat name="type" value="FVG"/>
   </struct>
   <struct type="VG" from="11369" to="11372">
      <feat name="voice" value="active"/>
      <feat name="tense" value="SimPre"/>
      <feat name="type" value="FVG"/>
   </struct>
   <struct type="VG" from="11415" to="11423">
      <feat name="voice" value="active"/>
      <feat name="tense" value="SimPas"/>
      <feat name="type" value="FVG"/>
   </struct>
   <struct type="VG" from="11522" to="11524">
      <feat name="voice" value="active"/>
      <feat name="tense" value="SimPre"/>
      <feat name="type" value="FVG"/>
   </struct>
   <struct type="VG" from="11600" to="11607">
      <feat name="voice" value="active"/>
      <feat name="tense" value="SimPre"/>
      <feat name="type" value="FVG"/>
   </struct>
   <struct type="VG" from="11619" to="11628">
      <feat name="voice" value="active"/>
      <feat name="tense" value="Pre"/>
      <feat name="type" value="PART"/>
   </struct>
   <struct type="VG" from="11688" to="11690">
      <feat name="voice" value="active"/>
      <feat name="tense" value="SimPre"/>
      <feat name="type" value="FVG"/>
   </struct>
   <struct type="VG" from="11753" to="11755">
      <feat name="voice" value="active"/>
      <feat name="tense" value="SimPre"/>
      <feat name="type" value="FVG"/>
   </struct>
   <struct type="VG" from="11804" to="11809">
      <feat name="voice" value="active"/>
      <feat name="tense" value="SimPre"/>
      <feat name="type" value="FVG"/>
   </struct>
   <struct type="VG" from="11939" to="11941">
      <feat name="voice" value="active"/>
      <feat name="tense" value="SimPre"/>
      <feat name="type" value="FVG"/>
   </struct>
   <struct type="VG" from="12070" to="12079">
      <feat name="voice" value="none"/>
      <feat name="tense" value="none"/>
      <feat name="type" value="MODAL"/>
   </struct>
   <struct type="VG" from="12191" to="12194">
      <feat name="voice" value="active"/>
      <feat name="tense" value="SimPre"/>
      <feat name="type" value="FVG"/>
   </struct>
   <struct type="VG" from="12292" to="12301">
      <feat name="voice" value="active"/>
      <feat name="tense" value="Inf"/>
      <feat name="type" value="NFVG"/>
   </struct>
   <struct type="VG" from="12468" to="12491">
      <feat name="voice" value="none"/>
      <feat name="tense" value="none"/>
      <feat name="type" value="MODAL"/>
   </struct>
   <struct type="VG" from="12591" to="12596">
      <feat name="voice" value="none"/>
      <feat name="tense" value="Pas"/>
      <feat name="type" value="PART"/>
   </struct>
   <struct type="VG" from="12661" to="12685">
      <feat name="voice" value="passive"/>
      <feat name="tense" value="SimPre"/>
      <feat name="type" value="FVG"/>
   </struct>
   <struct type="VG" from="12726" to="12729">
      <feat name="voice" value="active"/>
      <feat name="tense" value="SimPre"/>
      <feat name="type" value="FVG"/>
   </struct>
   <struct type="VG" from="12816" to="12827">
      <feat name="voice" value="none"/>
      <feat name="tense" value="none"/>
      <feat name="type" value="MODAL"/>
   </struct>
   <struct type="VG" from="12898" to="12900">
      <feat name="voice" value="active"/>
      <feat name="tense" value="SimPre"/>
      <feat name="type" value="FVG"/>
   </struct>
   <struct type="VG" from="12987" to="12994">
      <feat name="voice" value="active"/>
      <feat name="tense" value="SimPas"/>
      <feat name="type" value="FVG"/>
   </struct>
   <struct type="VG" from="13075" to="13084">
      <feat name="voice" value="active"/>
      <feat name="tense" value="Pre"/>
      <feat name="type" value="PART"/>
   </struct>
   <struct type="VG" from="13093" to="13112">
      <feat name="voice" value="none"/>
      <feat name="tense" value="BeVBN"/>
      <feat name="type" value="MODAL"/>
   </struct>
   <struct type="VG" from="13183" to="13188">
      <feat name="voice" value="active"/>
      <feat name="tense" value="SimPre"/>
      <feat name="type" value="FVG"/>
   </struct>
   <struct type="VG" from="13205" to="13208">
      <feat name="voice" value="active"/>
      <feat name="tense" value="SimPre"/>
      <feat name="type" value="FVG"/>
   </struct>
   <struct type="VG" from="13329" to="13334">
      <feat name="voice" value="none"/>
      <feat name="tense" value="Pas"/>
      <feat name="type" value="PART"/>
   </struct>
   <struct type="VG" from="13368" to="13376">
      <feat name="voice" value="active"/>
      <feat name="tense" value="SimPre"/>
      <feat name="type" value="FVG"/>
   </struct>
   <struct type="VG" from="13377" to="13386">
      <feat name="voice" value="active"/>
      <feat name="tense" value="Pre"/>
      <feat name="type" value="PART"/>
   </struct>
   <struct type="VG" from="13499" to="13507">
      <feat name="voice" value="active"/>
      <feat name="tense" value="SimPre"/>
      <feat name="type" value="FVG"/>
   </struct>
   <struct type="VG" from="13638" to="13646">
      <feat name="voice" value="active"/>
      <feat name="tense" value="Pre"/>
      <feat name="type" value="PART"/>
   </struct>
   <struct type="VG" from="13791" to="13801">
      <feat name="voice" value="none"/>
      <feat name="tense" value="none"/>
      <feat name="type" value="MODAL"/>
   </struct>
   <struct type="VG" from="13815" to="13821">
      <feat name="voice" value="none"/>
      <feat name="tense" value="Pas"/>
      <feat name="type" value="PART"/>
   </struct>
   <struct type="VG" from="13835" to="13848">
      <feat name="voice" value="none"/>
      <feat name="tense" value="Pas"/>
      <feat name="type" value="PART"/>
   </struct>
   <struct type="VG" from="13881" to="13913">
      <feat name="type" value="FVG"/>
      <feat name="tense" value="PrePer"/>
      <feat name="voice" value="passive"/>
      <feat name="neg" value="yes"/>
   </struct>
   <struct type="VG" from="14019" to="14026">
      <feat name="voice" value="active"/>
      <feat name="tense" value="SimPas"/>
      <feat name="type" value="FVG"/>
   </struct>
   <struct type="VG" from="14085" to="14090">
      <feat name="voice" value="active"/>
      <feat name="tense" value="Pre"/>
      <feat name="type" value="PART"/>
   </struct>
   <struct type="VG" from="14117" to="14127">
      <feat name="voice" value="active"/>
      <feat name="tense" value="Inf"/>
      <feat name="type" value="NFVG"/>
   </struct>
   <struct type="VG" from="14196" to="14212">
      <feat name="voice" value="none"/>
      <feat name="tense" value="none"/>
      <feat name="type" value="MODAL"/>
   </struct>
   <struct type="VG" from="14241" to="14257">
      <feat name="voice" value="none"/>
      <feat name="tense" value="BeVBN"/>
      <feat name="type" value="MODAL"/>
   </struct>
   <struct type="VG" from="14291" to="14301">
      <feat name="voice" value="passive"/>
      <feat name="tense" value="SimPre"/>
      <feat name="type" value="FVG"/>
   </struct>
   <struct type="VG" from="14317" to="14328">
      <feat name="voice" value="none"/>
      <feat name="tense" value="BeVBN"/>
      <feat name="type" value="MODAL"/>
   </struct>
   <struct type="VG" from="14378" to="14382">
      <feat name="voice" value="none"/>
      <feat name="tense" value="Pas"/>
      <feat name="type" value="PART"/>
   </struct>
   <struct type="VG" from="14391" to="14396">
      <feat name="voice" value="active"/>
      <feat name="tense" value="SimPre"/>
      <feat name="type" value="FVG"/>
   </struct>
   <struct type="VG" from="14514" to="14527">
      <feat name="voice" value="active"/>
      <feat name="tense" value="PrePer"/>
      <feat name="type" value="FVG"/>
   </struct>
   <struct type="VG" from="14588" to="14593">
      <feat name="voice" value="active"/>
      <feat name="tense" value="Pre"/>
      <feat name="type" value="PART"/>
   </struct>
   <struct type="VG" from="14676" to="14683">
      <feat name="voice" value="none"/>
      <feat name="tense" value="Pas"/>
      <feat name="type" value="PART"/>
   </struct>
   <struct type="VG" from="14714" to="14725">
      <feat name="voice" value="passive"/>
      <feat name="tense" value="SimPre"/>
      <feat name="type" value="FVG"/>
   </struct>
   <struct type="VG" from="14726" to="14731">
      <feat name="voice" value="active"/>
      <feat name="tense" value="Pre"/>
      <feat name="type" value="PART"/>
   </struct>
   <struct type="VG" from="14779" to="14788">
      <feat name="voice" value="active"/>
      <feat name="tense" value="Pre"/>
      <feat name="type" value="PART"/>
   </struct>
   <struct type="VG" from="14892" to="14904">
      <feat name="voice" value="active"/>
      <feat name="tense" value="Pre"/>
      <feat name="type" value="PART"/>
   </struct>
   <struct type="VG" from="14925" to="14934">
      <feat name="voice" value="active"/>
      <feat name="tense" value="SimFut"/>
      <feat name="type" value="FVG"/>
   </struct>
   <struct type="VG" from="15031" to="15038">
      <feat name="voice" value="active"/>
      <feat name="tense" value="SimPas"/>
      <feat name="type" value="FVG"/>
   </struct>
   <struct type="VG" from="15063" to="15073">
      <feat name="voice" value="active"/>
      <feat name="tense" value="Inf"/>
      <feat name="type" value="NFVG"/>
   </struct>
   <struct type="VG" from="15147" to="15157">
      <feat name="voice" value="active"/>
      <feat name="tense" value="SimPas"/>
      <feat name="type" value="FVG"/>
   </struct>
   <struct type="VG" from="15176" to="15178">
      <feat name="voice" value="active"/>
      <feat name="tense" value="SimPre"/>
      <feat name="type" value="FVG"/>
   </struct>
   <struct type="VG" from="15184" to="15196">
      <feat name="voice" value="active"/>
      <feat name="tense" value="Inf"/>
      <feat name="type" value="NFVG"/>
   </struct>
   <struct type="VG" from="15244" to="15247">
      <feat name="voice" value="active"/>
      <feat name="tense" value="SimPre"/>
      <feat name="type" value="FVG"/>
   </struct>
   <struct type="VG" from="15309" to="15320">
      <feat name="type" value="FVG"/>
      <feat name="tense" value="SimPre"/>
      <feat name="voice" value="active"/>
      <feat name="neg" value="yes"/>
   </struct>
   <struct type="VG" from="15364" to="15379">
      <feat name="type" value="FVG"/>
      <feat name="tense" value="SimPas"/>
      <feat name="voice" value="active"/>
      <feat name="neg" value="yes"/>
   </struct>
   <struct type="VG" from="15463" to="15471">
      <feat name="voice" value="passive"/>
      <feat name="tense" value="SimPre"/>
      <feat name="type" value="FVG"/>
   </struct>
   <struct type="VG" from="15546" to="15553">
      <feat name="voice" value="active"/>
      <feat name="tense" value="SimPas"/>
      <feat name="type" value="FVG"/>
   </struct>
   <struct type="VG" from="15564" to="15574">
      <feat name="voice" value="active"/>
      <feat name="tense" value="Pre"/>
      <feat name="type" value="PART"/>
   </struct>
   <struct type="VG" from="15604" to="15615">
      <feat name="voice" value="active"/>
      <feat name="tense" value="Pre"/>
      <feat name="type" value="PART"/>
   </struct>
   <struct type="VG" from="15713" to="15715">
      <feat name="voice" value="active"/>
      <feat name="tense" value="SimPre"/>
      <feat name="type" value="FVG"/>
   </struct>
   <struct type="VG" from="15726" to="15737">
      <feat name="voice" value="active"/>
      <feat name="tense" value="Inf"/>
      <feat name="type" value="NFVG"/>
   </struct>
   <struct type="VG" from="15785" to="15790">
      <feat name="voice" value="active"/>
      <feat name="tense" value="Pre"/>
      <feat name="type" value="PART"/>
   </struct>
   <struct type="VG" from="15972" to="15977">
      <feat name="voice" value="active"/>
      <feat name="tense" value="SimPre"/>
      <feat name="type" value="FVG"/>
   </struct>
   <struct type="VG" from="15988" to="16015">
      <feat name="voice" value="none"/>
      <feat name="tense" value="BeVBN"/>
      <feat name="type" value="MODAL"/>
   </struct>
   <struct type="VG" from="16051" to="16059">
      <feat name="voice" value="active"/>
      <feat name="tense" value="SimPre"/>
      <feat name="type" value="FVG"/>
   </struct>
   <struct type="VG" from="16174" to="16180">
      <feat name="voice" value="active"/>
      <feat name="tense" value="SimPre"/>
      <feat name="type" value="FVG"/>
   </struct>
   <struct type="VG" from="16289" to="16296">
      <feat name="voice" value="active"/>
      <feat name="tense" value="SimPas"/>
      <feat name="type" value="FVG"/>
   </struct>
   <struct type="VG" from="16390" to="16397">
      <feat name="voice" value="active"/>
      <feat name="tense" value="Inf"/>
      <feat name="type" value="NFVG"/>
   </struct>
   <struct type="VG" from="16505" to="16512">
      <feat name="voice" value="active"/>
      <feat name="tense" value="SimPas"/>
      <feat name="type" value="FVG"/>
   </struct>
   <struct type="VG" from="16751" to="16754">
      <feat name="voice" value="active"/>
      <feat name="tense" value="SimPre"/>
      <feat name="type" value="FVG"/>
   </struct>
   <struct type="VG" from="16810" to="16820">
      <feat name="voice" value="active"/>
      <feat name="tense" value="Inf"/>
      <feat name="type" value="NFVG"/>
   </struct>
   <struct type="VG" from="16851" to="16859">
      <feat name="voice" value="active"/>
      <feat name="tense" value="SimPas"/>
      <feat name="type" value="FVG"/>
   </struct>
   <struct type="VG" from="16928" to="16938">
      <feat name="voice" value="active"/>
      <feat name="tense" value="SimPas"/>
      <feat name="type" value="FVG"/>
   </struct>
   <struct type="VG" from="16992" to="16995">
      <feat name="voice" value="active"/>
      <feat name="tense" value="SimPre"/>
      <feat name="type" value="FVG"/>
   </struct>
   <struct type="VG" from="17054" to="17056">
      <feat name="voice" value="active"/>
      <feat name="tense" value="SimPre"/>
      <feat name="type" value="FVG"/>
   </struct>
   <struct type="VG" from="17132" to="17140">
      <feat name="voice" value="active"/>
      <feat name="tense" value="SimPas"/>
      <feat name="type" value="FVG"/>
   </struct>
   <struct type="VG" from="17154" to="17159">
      <feat name="voice" value="none"/>
      <feat name="tense" value="Pas"/>
      <feat name="type" value="PART"/>
   </struct>
   <struct type="VG" from="17186" to="17189">
      <feat name="voice" value="active"/>
      <feat name="tense" value="Inf"/>
      <feat name="type" value="NFVG"/>
   </struct>
   <struct type="VG" from="17203" to="17205">
      <feat name="voice" value="active"/>
      <feat name="tense" value="Inf"/>
      <feat name="type" value="NFVG"/>
   </struct>
   <struct type="VG" from="17249" to="17255">
      <feat name="voice" value="none"/>
      <feat name="tense" value="Pas"/>
      <feat name="type" value="PART"/>
   </struct>
   <struct type="VG" from="17291" to="17293">
      <feat name="voice" value="active"/>
      <feat name="tense" value="SimPre"/>
      <feat name="type" value="FVG"/>
   </struct>
   <struct type="VG" from="17342" to="17352">
      <feat name="voice" value="passive"/>
      <feat name="tense" value="SimPre"/>
      <feat name="type" value="FVG"/>
   </struct>
   <struct type="VG" from="17375" to="17378">
      <feat name="voice" value="active"/>
      <feat name="tense" value="SimPre"/>
      <feat name="type" value="FVG"/>
   </struct>
   <struct type="VG" from="17446" to="17469">
      <feat name="voice" value="passive"/>
      <feat name="tense" value="SimPre"/>
      <feat name="type" value="FVG"/>
   </struct>
   <struct type="VG" from="17531" to="17537">
      <feat name="voice" value="active"/>
      <feat name="tense" value="SimPre"/>
      <feat name="type" value="FVG"/>
   </struct>
   <struct type="VG" from="17559" to="17561">
      <feat name="voice" value="active"/>
      <feat name="tense" value="SimPre"/>
      <feat name="type" value="FVG"/>
   </struct>
   <struct type="VG" from="17656" to="17658">
      <feat name="voice" value="active"/>
      <feat name="tense" value="SimPre"/>
      <feat name="type" value="FVG"/>
   </struct>
   <struct type="VG" from="17659" to="17666">
      <feat name="voice" value="active"/>
      <feat name="tense" value="SimPas"/>
      <feat name="type" value="FVG"/>
   </struct>
   <struct type="VG" from="17771" to="17774">
      <feat name="voice" value="active"/>
      <feat name="tense" value="SimPre"/>
      <feat name="type" value="FVG"/>
   </struct>
   <struct type="VG" from="17785" to="17793">
      <feat name="voice" value="active"/>
      <feat name="tense" value="SimPre"/>
      <feat name="type" value="FVG"/>
   </struct>
   <struct type="VG" from="17991" to="17995">
      <feat name="voice" value="active"/>
      <feat name="tense" value="SimPre"/>
      <feat name="type" value="FVG"/>
   </struct>
   <struct type="VG" from="18047" to="18059">
      <feat name="voice" value="passive"/>
      <feat name="tense" value="SimPre"/>
      <feat name="type" value="FVG"/>
   </struct>
   <struct type="VG" from="18154" to="18156">
      <feat name="voice" value="active"/>
      <feat name="tense" value="SimPre"/>
      <feat name="type" value="FVG"/>
   </struct>
   <struct type="VG" from="18176" to="18182">
      <feat name="voice" value="active"/>
      <feat name="tense" value="Pre"/>
      <feat name="type" value="PART"/>
   </struct>
   <struct type="VG" from="18276" to="18278">
      <feat name="voice" value="active"/>
      <feat name="tense" value="SimPre"/>
      <feat name="type" value="FVG"/>
   </struct>
   <struct type="VG" from="18298" to="18304">
      <feat name="voice" value="active"/>
      <feat name="tense" value="Pre"/>
      <feat name="type" value="PART"/>
   </struct>
   <struct type="VG" from="18349" to="18356">
      <feat name="voice" value="none"/>
      <feat name="tense" value="Pas"/>
      <feat name="type" value="PART"/>
   </struct>
   <struct type="VG" from="18449" to="18451">
      <feat name="voice" value="active"/>
      <feat name="tense" value="SimPre"/>
      <feat name="type" value="FVG"/>
   </struct>
   <struct type="VG" from="18502" to="18503">
      <feat name="voice" value="active"/>
      <feat name="tense" value="SimPre"/>
      <feat name="type" value="FVG"/>
   </struct>
   <struct type="VG" from="18529" to="18532">
      <feat name="voice" value="active"/>
      <feat name="tense" value="SimPre"/>
      <feat name="type" value="FVG"/>
   </struct>
   <struct type="VG" from="18534" to="18535">
      <feat name="voice" value="active"/>
      <feat name="tense" value="SimPre"/>
      <feat name="type" value="FVG"/>
   </struct>
   <struct type="VG" from="18665" to="18681">
      <feat name="voice" value="none"/>
      <feat name="tense" value="BeVBN"/>
      <feat name="type" value="MODAL"/>
   </struct>
   <struct type="VG" from="18685" to="18696">
      <feat name="voice" value="active"/>
      <feat name="tense" value="Pre"/>
      <feat name="type" value="PART"/>
   </struct>
   <struct type="VG" from="18750" to="18752">
      <feat name="voice" value="active"/>
      <feat name="tense" value="SimPre"/>
      <feat name="type" value="FVG"/>
   </struct>
   <struct type="VG" from="18794" to="18796">
      <feat name="voice" value="active"/>
      <feat name="tense" value="SimPre"/>
      <feat name="type" value="FVG"/>
   </struct>
   <struct type="VG" from="18981" to="18987">
      <feat name="voice" value="active"/>
      <feat name="tense" value="SimPre"/>
      <feat name="type" value="FVG"/>
   </struct>
   <struct type="VG" from="19009" to="19015">
      <feat name="voice" value="active"/>
      <feat name="tense" value="Inf"/>
      <feat name="type" value="NFVG"/>
   </struct>
   <struct type="VG" from="19047" to="19076">
      <feat name="type" value="FVG"/>
      <feat name="tense" value="SimPre"/>
      <feat name="voice" value="active"/>
      <feat name="neg" value="yes"/>
   </struct>
   <struct type="VG" from="19115" to="19122">
      <feat name="voice" value="none"/>
      <feat name="tense" value="none"/>
      <feat name="type" value="MODAL"/>
   </struct>
   <struct type="VG" from="19146" to="19149">
      <feat name="voice" value="active"/>
      <feat name="tense" value="SimPre"/>
      <feat name="type" value="FVG"/>
   </struct>
   <struct type="VG" from="19212" to="19217">
      <feat name="voice" value="active"/>
      <feat name="tense" value="SimPre"/>
      <feat name="type" value="FVG"/>
   </struct>
   <struct type="VG" from="19218" to="19239">
      <feat name="voice" value="active"/>
      <feat name="tense" value="Inf"/>
      <feat name="type" value="NFVG"/>
   </struct>
   <struct type="VG" from="19254" to="19264">
      <feat name="voice" value="active"/>
      <feat name="tense" value="Pre"/>
      <feat name="type" value="PART"/>
   </struct>
   <struct type="VG" from="19334" to="19336">
      <feat name="voice" value="active"/>
      <feat name="tense" value="SimPre"/>
      <feat name="type" value="FVG"/>
   </struct>
   <struct type="VG" from="19347" to="19367">
      <feat name="voice" value="active"/>
      <feat name="tense" value="Inf"/>
      <feat name="type" value="NFVG"/>
   </struct>
   <struct type="VG" from="19406" to="19431">
      <feat name="voice" value="passive"/>
      <feat name="tense" value="SimPre"/>
      <feat name="type" value="FVG"/>
   </struct>
   <struct type="VG" from="19445" to="19448">
      <feat name="voice" value="active"/>
      <feat name="tense" value="SimPre"/>
      <feat name="type" value="FVG"/>
   </struct>
   <struct type="VG" from="19574" to="19585">
      <feat name="voice" value="active"/>
      <feat name="tense" value="PrePer"/>
      <feat name="type" value="FVG"/>
   </struct>
   <struct type="VG" from="19600" to="19602">
      <feat name="voice" value="active"/>
      <feat name="tense" value="SimPre"/>
      <feat name="type" value="FVG"/>
   </struct>
   <struct type="VG" from="19611" to="19627">
      <feat name="voice" value="active"/>
      <feat name="tense" value="Inf"/>
      <feat name="type" value="NFVG"/>
   </struct>
   <struct type="VG" from="19668" to="19677">
      <feat name="voice" value="active"/>
      <feat name="tense" value="SimFut"/>
      <feat name="type" value="FVG"/>
   </struct>
   <struct type="VG" from="19691" to="19698">
      <feat name="voice" value="active"/>
      <feat name="tense" value="Inf"/>
      <feat name="type" value="NFVG"/>
   </struct>
   <struct type="VG" from="19823" to="19842">
      <feat name="voice" value="none"/>
      <feat name="tense" value="Pre"/>
      <feat name="type" value="SPECIAL"/>
   </struct>
   <struct type="VG" from="19917" to="19922">
      <feat name="voice" value="active"/>
      <feat name="tense" value="Pre"/>
      <feat name="type" value="PART"/>
   </struct>
   <struct type="VG" from="20108" to="20115">
      <feat name="voice" value="none"/>
      <feat name="tense" value="none"/>
      <feat name="type" value="MODAL"/>
   </struct>
   <struct type="VG" from="20163" to="20174">
      <feat name="voice" value="passive"/>
      <feat name="tense" value="SimPre"/>
      <feat name="type" value="FVG"/>
   </struct>
   <struct type="VG" from="20223" to="20235">
      <feat name="voice" value="passive"/>
      <feat name="tense" value="SimPre"/>
      <feat name="type" value="FVG"/>
   </struct>
   <struct type="VG" from="20258" to="20262">
      <feat name="voice" value="active"/>
      <feat name="tense" value="SimPre"/>
      <feat name="type" value="FVG"/>
   </struct>
   <struct type="VG" from="20263" to="20272">
      <feat name="voice" value="active"/>
      <feat name="tense" value="Inf"/>
      <feat name="type" value="NFVG"/>
   </struct>
   <struct type="VG" from="20304" to="20315">
      <feat name="type" value="FVG"/>
      <feat name="tense" value="SimPas"/>
      <feat name="voice" value="active"/>
      <feat name="neg" value="yes"/>
   </struct>
   <struct type="VG" from="20353" to="20358">
      <feat name="voice" value="active"/>
      <feat name="tense" value="Pre"/>
      <feat name="type" value="PART"/>
   </struct>
   <struct type="VG" from="20392" to="20396">
      <feat name="voice" value="active"/>
      <feat name="tense" value="SimPas"/>
      <feat name="type" value="FVG"/>
   </struct>
   <struct type="VG" from="20400" to="20405">
      <feat name="voice" value="active"/>
      <feat name="tense" value="SimPre"/>
      <feat name="type" value="FVG"/>
   </struct>
   <struct type="VG" from="20422" to="20428">
      <feat name="voice" value="none"/>
      <feat name="tense" value="none"/>
      <feat name="type" value="MODAL"/>
   </struct>
   <struct type="VG" from="20524" to="20546">
      <feat name="voice" value="passive"/>
      <feat name="tense" value="SimPre"/>
      <feat name="type" value="FVG"/>
   </struct>
   <struct type="VG" from="20607" to="20610">
      <feat name="voice" value="active"/>
      <feat name="tense" value="SimPre"/>
      <feat name="type" value="FVG"/>
   </struct>
   <struct type="VG" from="20612" to="20621">
      <feat name="voice" value="none"/>
      <feat name="tense" value="Pas"/>
      <feat name="type" value="PART"/>
   </struct>
   <struct type="VG" from="20630" to="20646">
      <feat name="voice" value="none"/>
      <feat name="tense" value="none"/>
      <feat name="type" value="MODAL"/>
   </struct>
   <struct type="VG" from="20697" to="20707">
      <feat name="voice" value="active"/>
      <feat name="tense" value="Inf"/>
      <feat name="type" value="NFVG"/>
   </struct>
   <struct type="VG" from="20755" to="20763">
      <feat name="voice" value="none"/>
      <feat name="tense" value="Pas"/>
      <feat name="type" value="PART"/>
   </struct>
   <struct type="VG" from="20771" to="20774">
      <feat name="voice" value="none"/>
      <feat name="tense" value="Pas"/>
      <feat name="type" value="PART"/>
   </struct>
   <struct type="VG" from="20785" to="20795">
      <feat name="voice" value="passive"/>
      <feat name="tense" value="SimPre"/>
      <feat name="type" value="FVG"/>
   </struct>
   <struct type="VG" from="20812" to="20820">
      <feat name="voice" value="active"/>
      <feat name="tense" value="Pre"/>
      <feat name="type" value="PART"/>
   </struct>
   <struct type="VG" from="20830" to="20837">
      <feat name="voice" value="passive"/>
      <feat name="tense" value="SimPre"/>
      <feat name="type" value="FVG"/>
   </struct>
   <struct type="VG" from="20925" to="20936">
      <feat name="voice" value="active"/>
      <feat name="tense" value="SimPre"/>
      <feat name="type" value="FVG"/>
   </struct>
   <struct type="VG" from="20958" to="20966">
      <feat name="voice" value="none"/>
      <feat name="tense" value="Pas"/>
      <feat name="type" value="PART"/>
   </struct>
   <struct type="VG" from="20986" to="20991">
      <feat name="voice" value="active"/>
      <feat name="tense" value="SimPre"/>
      <feat name="type" value="FVG"/>
   </struct>
   <struct type="VG" from="21038" to="21054">
      <feat name="voice" value="active"/>
      <feat name="tense" value="Inf"/>
      <feat name="type" value="NFVG"/>
   </struct>
   <struct type="VG" from="21117" to="21124">
      <feat name="voice" value="active"/>
      <feat name="tense" value="Inf"/>
      <feat name="type" value="NFVG"/>
   </struct>
   <struct type="VG" from="21209" to="21217">
      <feat name="voice" value="active"/>
      <feat name="tense" value="SimPas"/>
      <feat name="type" value="FVG"/>
   </struct>
   <struct type="VG" from="21271" to="21282">
      <feat name="voice" value="none"/>
      <feat name="tense" value="Pas"/>
      <feat name="type" value="PART"/>
   </struct>
   <struct type="VG" from="21320" to="21342">
      <feat name="voice" value="none"/>
      <feat name="tense" value="BeVBN"/>
      <feat name="type" value="MODAL"/>
   </struct>
   <struct type="VG" from="21384" to="21388">
      <feat name="voice" value="active"/>
      <feat name="tense" value="SimPre"/>
      <feat name="type" value="FVG"/>
   </struct>
   <struct type="VG" from="21419" to="21427">
      <feat name="voice" value="none"/>
      <feat name="tense" value="Pas"/>
      <feat name="type" value="PART"/>
   </struct>
   <struct type="VG" from="21448" to="21454">
      <feat name="voice" value="none"/>
      <feat name="tense" value="none"/>
      <feat name="type" value="MODAL"/>
   </struct>
   <struct type="VG" from="21498" to="21503">
      <feat name="voice" value="none"/>
      <feat name="tense" value="Pas"/>
      <feat name="type" value="PART"/>
   </struct>
   <struct type="VG" from="21512" to="21520">
      <feat name="voice" value="active"/>
      <feat name="tense" value="SimPre"/>
      <feat name="type" value="FVG"/>
   </struct>
   <struct type="VG" from="21591" to="21594">
      <feat name="voice" value="active"/>
      <feat name="tense" value="SimPre"/>
      <feat name="type" value="FVG"/>
   </struct>
   <struct type="VG" from="21642" to="21653">
      <feat name="voice" value="passive"/>
      <feat name="tense" value="SimPre"/>
      <feat name="type" value="FVG"/>
   </struct>
   <struct type="VG" from="21668" to="21674">
      <feat name="voice" value="active"/>
      <feat name="tense" value="Inf"/>
      <feat name="type" value="NFVG"/>
   </struct>
   <struct type="VG" from="21675" to="21684">
      <feat name="voice" value="active"/>
      <feat name="tense" value="Inf"/>
      <feat name="type" value="NFVG"/>
   </struct>
   <struct type="VG" from="21740" to="21759">
      <feat name="voice" value="none"/>
      <feat name="tense" value="BeVBN"/>
      <feat name="type" value="MODAL"/>
   </struct>
   <struct type="VG" from="21778" to="21786">
      <feat name="voice" value="passive"/>
      <feat name="tense" value="SimPre"/>
      <feat name="type" value="FVG"/>
   </struct>
   <struct type="VG" from="21828" to="21833">
      <feat name="voice" value="active"/>
      <feat name="tense" value="Pre"/>
      <feat name="type" value="PART"/>
   </struct>
   <struct type="VG" from="21845" to="21854">
      <feat name="voice" value="active"/>
      <feat name="tense" value="SimPre"/>
      <feat name="type" value="FVG"/>
   </struct>
   <struct type="VG" from="21910" to="21913">
      <feat name="voice" value="active"/>
      <feat name="tense" value="Inf"/>
      <feat name="type" value="NFVG"/>
   </struct>
   <struct type="VG" from="21975" to="22004">
      <feat name="voice" value="passive"/>
      <feat name="tense" value="SimPre"/>
      <feat name="type" value="FVG"/>
   </struct>
   <struct type="VG" from="22087" to="22089">
      <feat name="voice" value="active"/>
      <feat name="tense" value="SimPre"/>
      <feat name="type" value="FVG"/>
   </struct>
   <struct type="VG" from="22100" to="22110">
      <feat name="voice" value="active"/>
      <feat name="tense" value="Inf"/>
      <feat name="type" value="NFVG"/>
   </struct>
   <struct type="VG" from="22162" to="22164">
      <feat name="voice" value="active"/>
      <feat name="tense" value="SimPre"/>
      <feat name="type" value="FVG"/>
   </struct>
   <struct type="VG" from="22207" to="22215">
      <feat name="voice" value="active"/>
      <feat name="tense" value="SimPas"/>
      <feat name="type" value="FVG"/>
   </struct>
   <struct type="VG" from="22277" to="22284">
      <feat name="voice" value="active"/>
      <feat name="tense" value="SimFut"/>
      <feat name="type" value="FVG"/>
   </struct>
   <struct type="VG" from="22285" to="22293">
      <feat name="voice" value="none"/>
      <feat name="tense" value="Pas"/>
      <feat name="type" value="PART"/>
   </struct>
   <struct type="VG" from="22331" to="22339">
      <feat name="voice" value="active"/>
      <feat name="tense" value="Pre"/>
      <feat name="type" value="PART"/>
   </struct>
   <struct type="VG" from="22368" to="22390">
      <feat name="voice" value="passive"/>
      <feat name="tense" value="SimPre"/>
      <feat name="type" value="FVG"/>
   </struct>
   <struct type="VG" from="22449" to="22456">
      <feat name="voice" value="active"/>
      <feat name="tense" value="SimPre"/>
      <feat name="type" value="FVG"/>
   </struct>
   <struct type="VG" from="22471" to="22478">
      <feat name="voice" value="active"/>
      <feat name="tense" value="Inf"/>
      <feat name="type" value="NFVG"/>
   </struct>
   <struct type="VG" from="22645" to="22651">
      <feat name="voice" value="active"/>
      <feat name="tense" value="SimPre"/>
      <feat name="type" value="FVG"/>
   </struct>
   <struct type="VG" from="22694" to="22696">
      <feat name="voice" value="active"/>
      <feat name="tense" value="SimPre"/>
      <feat name="type" value="FVG"/>
   </struct>
   <struct type="VG" from="22758" to="22760">
      <feat name="voice" value="active"/>
      <feat name="tense" value="SimPre"/>
      <feat name="type" value="FVG"/>
   </struct>
   <struct type="VG" from="22822" to="22832">
      <feat name="voice" value="active"/>
      <feat name="tense" value="Pre"/>
      <feat name="type" value="PART"/>
   </struct>
   <struct type="VG" from="22897" to="22925">
      <feat name="voice" value="none"/>
      <feat name="tense" value="Pre"/>
      <feat name="type" value="SPECIAL"/>
   </struct>
   <struct type="VG" from="23006" to="23011">
      <feat name="voice" value="none"/>
      <feat name="tense" value="Pas"/>
      <feat name="type" value="PART"/>
   </struct>
   <struct type="VG" from="23105" to="23113">
      <feat name="voice" value="none"/>
      <feat name="tense" value="none"/>
      <feat name="type" value="MODAL"/>
   </struct>
   <struct type="VG" from="23289" to="23299">
      <feat name="voice" value="active"/>
      <feat name="tense" value="SimPre"/>
      <feat name="type" value="FVG"/>
   </struct>
   <struct type="VG" from="23401" to="23403">
      <feat name="voice" value="active"/>
      <feat name="tense" value="SimPre"/>
      <feat name="type" value="FVG"/>
   </struct>
   <struct type="VG" from="23491" to="23495">
      <feat name="voice" value="active"/>
      <feat name="tense" value="SimPre"/>
      <feat name="type" value="FVG"/>
   </struct>
   <struct type="VG" from="23496" to="23505">
      <feat name="voice" value="active"/>
      <feat name="tense" value="Inf"/>
      <feat name="type" value="NFVG"/>
   </struct>
   <struct type="VG" from="23614" to="23623">
      <feat name="voice" value="passive"/>
      <feat name="tense" value="SimPre"/>
      <feat name="type" value="FVG"/>
   </struct>
   <struct type="VG" from="23624" to="23631">
      <feat name="voice" value="active"/>
      <feat name="tense" value="Inf"/>
      <feat name="type" value="NFVG"/>
   </struct>
   <struct type="VG" from="23733" to="23740">
      <feat name="voice" value="none"/>
      <feat name="tense" value="Pas"/>
      <feat name="type" value="PART"/>
   </struct>
   <struct type="VG" from="23762" to="23771">
      <feat name="voice" value="active"/>
      <feat name="tense" value="SimPas"/>
      <feat name="type" value="FVG"/>
   </struct>
   <struct type="VG" from="23819" to="23824">
      <feat name="voice" value="active"/>
      <feat name="tense" value="SimPre"/>
      <feat name="type" value="FVG"/>
   </struct>
   <struct type="VG" from="23849" to="23861">
      <feat name="voice" value="active"/>
      <feat name="tense" value="Pre"/>
      <feat name="type" value="PART"/>
   </struct>
   <struct type="VG" from="23938" to="23945">
      <feat name="type" value="FVG"/>
      <feat name="tense" value="SimPre"/>
      <feat name="voice" value="active"/>
      <feat name="neg" value="yes"/>
   </struct>
   <struct type="VG" from="23946" to="23962">
      <feat name="voice" value="active"/>
      <feat name="tense" value="Inf"/>
      <feat name="type" value="NFVG"/>
   </struct>
   <struct type="VG" from="24047" to="24055">
      <feat name="voice" value="none"/>
      <feat name="tense" value="none"/>
      <feat name="type" value="MODAL"/>
   </struct>
   <struct type="VG" from="24059" to="24069">
      <feat name="voice" value="active"/>
      <feat name="tense" value="Inf"/>
      <feat name="type" value="NFVG"/>
   </struct>
   <struct type="VG" from="24201" to="24210">
      <feat name="voice" value="active"/>
      <feat name="tense" value="SimPas"/>
      <feat name="type" value="FVG"/>
   </struct>
   <struct type="VG" from="24271" to="24294">
      <feat name="voice" value="none"/>
      <feat name="tense" value="none"/>
      <feat name="type" value="MODAL"/>
   </struct>
   <struct type="VG" from="24318" to="24327">
      <feat name="voice" value="active"/>
      <feat name="tense" value="Pre"/>
      <feat name="type" value="PART"/>
   </struct>
   <struct type="VG" from="24397" to="24409">
      <feat name="voice" value="none"/>
      <feat name="tense" value="none"/>
      <feat name="type" value="MODAL"/>
   </struct>
   <struct type="VG" from="24410" to="24416">
      <feat name="voice" value="active"/>
      <feat name="tense" value="Inf"/>
      <feat name="type" value="NFVG"/>
   </struct>
   <struct type="VG" from="24501" to="24509">
      <feat name="voice" value="active"/>
      <feat name="tense" value="SimPas"/>
      <feat name="type" value="FVG"/>
   </struct>
   <struct type="VG" from="24576" to="24582">
      <feat name="voice" value="active"/>
      <feat name="tense" value="Inf"/>
      <feat name="type" value="NFVG"/>
   </struct>
   <struct type="VG" from="24639" to="24647">
      <feat name="voice" value="active"/>
      <feat name="tense" value="SimPre"/>
      <feat name="type" value="FVG"/>
   </struct>
   <struct type="VG" from="24773" to="24782">
      <feat name="voice" value="passive"/>
      <feat name="tense" value="SimPre"/>
      <feat name="type" value="FVG"/>
   </struct>
   <struct type="VG" from="24939" to="24942">
      <feat name="voice" value="active"/>
      <feat name="tense" value="SimPre"/>
      <feat name="type" value="FVG"/>
   </struct>
   <struct type="VG" from="24943" to="24952">
      <feat name="voice" value="active"/>
      <feat name="tense" value="Inf"/>
      <feat name="type" value="NFVG"/>
   </struct>
   <struct type="VG" from="25005" to="25010">
      <feat name="voice" value="none"/>
      <feat name="tense" value="Pas"/>
      <feat name="type" value="PART"/>
   </struct>
   <struct type="VG" from="25020" to="25029">
      <feat name="voice" value="active"/>
      <feat name="tense" value="Pre"/>
      <feat name="type" value="PART"/>
   </struct>
   <struct type="VG" from="25252" to="25269">
      <feat name="voice" value="none"/>
      <feat name="tense" value="Pre"/>
      <feat name="type" value="SPECIAL"/>
   </struct>
   <struct type="VG" from="25308" to="25319">
      <feat name="voice" value="active"/>
      <feat name="tense" value="Pre"/>
      <feat name="type" value="PART"/>
   </struct>
   <struct type="VG" from="25477" to="25488">
      <feat name="voice" value="passive"/>
      <feat name="tense" value="SimPre"/>
      <feat name="type" value="FVG"/>
   </struct>
   <struct type="VG" from="25499" to="25510">
      <feat name="voice" value="active"/>
      <feat name="tense" value="Inf"/>
      <feat name="type" value="NFVG"/>
   </struct>
   <struct type="VG" from="25515" to="25519">
      <feat name="voice" value="active"/>
      <feat name="tense" value="SimPre"/>
      <feat name="type" value="FVG"/>
   </struct>
   <struct type="VG" from="25540" to="25548">
      <feat name="voice" value="none"/>
      <feat name="tense" value="Pas"/>
      <feat name="type" value="PART"/>
   </struct>
   <struct type="VG" from="25707" to="25710">
      <feat name="voice" value="active"/>
      <feat name="tense" value="SimPre"/>
      <feat name="type" value="FVG"/>
   </struct>
   <struct type="VG" from="25718" to="25753">
      <feat name="voice" value="active"/>
      <feat name="tense" value="Inf"/>
      <feat name="type" value="NFVG"/>
   </struct>
   <struct type="VG" from="25766" to="25775">
      <feat name="voice" value="active"/>
      <feat name="tense" value="Inf"/>
      <feat name="type" value="NFVG"/>
   </struct>
   <struct type="VG" from="25906" to="25911">
      <feat name="voice" value="active"/>
      <feat name="tense" value="SimPas"/>
      <feat name="type" value="FVG"/>
   </struct>
   <struct type="VG" from="25958" to="25967">
      <feat name="voice" value="active"/>
      <feat name="tense" value="Pre"/>
      <feat name="type" value="PART"/>
   </struct>
   <struct type="VG" from="26037" to="26040">
      <feat name="voice" value="active"/>
      <feat name="tense" value="SimPas"/>
      <feat name="type" value="FVG"/>
   </struct>
   <struct type="VG" from="26109" to="26113">
      <feat name="voice" value="active"/>
      <feat name="tense" value="SimPas"/>
      <feat name="type" value="FVG"/>
   </struct>
   <struct type="VG" from="26147" to="26155">
      <feat name="voice" value="active"/>
      <feat name="tense" value="SimPas"/>
      <feat name="type" value="FVG"/>
   </struct>
   <struct type="VG" from="26193" to="26204">
      <feat name="voice" value="active"/>
      <feat name="tense" value="Inf"/>
      <feat name="type" value="NFVG"/>
   </struct>
   <struct type="VG" from="26275" to="26282">
      <feat name="voice" value="active"/>
      <feat name="tense" value="Inf"/>
      <feat name="type" value="NFVG"/>
   </struct>
   <struct type="VG" from="26349" to="26363">
      <feat name="voice" value="passive"/>
      <feat name="tense" value="SimPas"/>
      <feat name="type" value="FVG"/>
   </struct>
   <struct type="VG" from="26464" to="26469">
      <feat name="voice" value="active"/>
      <feat name="tense" value="SimPas"/>
      <feat name="type" value="FVG"/>
   </struct>
   <struct type="VG" from="26608" to="26620">
      <feat name="voice" value="active"/>
      <feat name="tense" value="Pre"/>
      <feat name="type" value="PART"/>
   </struct>
   <struct type="VG" from="26672" to="26681">
      <feat name="voice" value="active"/>
      <feat name="tense" value="SimPas"/>
      <feat name="type" value="FVG"/>
   </struct>
   <struct type="VG" from="26730" to="26741">
      <feat name="voice" value="active"/>
      <feat name="tense" value="Inf"/>
      <feat name="type" value="NFVG"/>
   </struct>
   <struct type="VG" from="26811" to="26822">
      <feat name="voice" value="active"/>
      <feat name="tense" value="Pre"/>
      <feat name="type" value="PART"/>
   </struct>
   <struct type="VG" from="26871" to="26882">
      <feat name="voice" value="active"/>
      <feat name="tense" value="Pre"/>
      <feat name="type" value="PART"/>
   </struct>
   <struct type="VG" from="26951" to="26967">
      <feat name="voice" value="none"/>
      <feat name="tense" value="Pre"/>
      <feat name="type" value="SPECIAL"/>
   </struct>
   <struct type="VG" from="27020" to="27023">
      <feat name="voice" value="active"/>
      <feat name="tense" value="SimPre"/>
      <feat name="type" value="FVG"/>
   </struct>
   <struct type="VG" from="27062" to="27070">
      <feat name="voice" value="none"/>
      <feat name="tense" value="Pas"/>
      <feat name="type" value="PART"/>
   </struct>
   <struct type="VG" from="27129" to="27131">
      <feat name="voice" value="active"/>
      <feat name="tense" value="SimPre"/>
      <feat name="type" value="FVG"/>
   </struct>
   <struct type="VG" from="27160" to="27163">
      <feat name="voice" value="active"/>
      <feat name="tense" value="SimPre"/>
      <feat name="type" value="FVG"/>
   </struct>
   <struct type="VG" from="27171" to="27181">
      <feat name="voice" value="active"/>
      <feat name="tense" value="Inf"/>
      <feat name="type" value="NFVG"/>
   </struct>
   <struct type="VG" from="27213" to="27219">
      <feat name="voice" value="active"/>
      <feat name="tense" value="SimPre"/>
      <feat name="type" value="FVG"/>
   </struct>
   <struct type="VG" from="27262" to="27265">
      <feat name="voice" value="active"/>
      <feat name="tense" value="SimPre"/>
      <feat name="type" value="FVG"/>
   </struct>
   <struct type="VG" from="27284" to="27294">
      <feat name="voice" value="active"/>
      <feat name="tense" value="Inf"/>
      <feat name="type" value="NFVG"/>
   </struct>
   <struct type="VG" from="27299" to="27306">
      <feat name="voice" value="active"/>
      <feat name="tense" value="Inf"/>
      <feat name="type" value="NFVG"/>
   </struct>
   <struct type="VG" from="27368" to="27371">
      <feat name="voice" value="active"/>
      <feat name="tense" value="SimPre"/>
      <feat name="type" value="FVG"/>
   </struct>
   <struct type="VG" from="27409" to="27418">
      <feat name="voice" value="none"/>
      <feat name="tense" value="Pas"/>
      <feat name="type" value="PART"/>
   </struct>
   <struct type="VG" from="27456" to="27460">
      <feat name="voice" value="active"/>
      <feat name="tense" value="SimPre"/>
      <feat name="type" value="FVG"/>
   </struct>
   <struct type="VG" from="27461" to="27482">
      <feat name="voice" value="passive"/>
      <feat name="tense" value="Inf"/>
      <feat name="type" value="NFVG"/>
   </struct>
   <struct type="VG" from="27483" to="27492">
      <feat name="voice" value="active"/>
      <feat name="tense" value="Inf"/>
      <feat name="type" value="NFVG"/>
   </struct>
   <struct type="VG" from="27562" to="27573">
      <feat name="voice" value="none"/>
      <feat name="tense" value="none"/>
      <feat name="type" value="MODAL"/>
   </struct>
   <struct type="VG" from="27792" to="27798">
      <feat name="voice" value="none"/>
      <feat name="tense" value="Pas"/>
      <feat name="type" value="PART"/>
   </struct>
   <struct type="VG" from="27821" to="27829">
      <feat name="voice" value="none"/>
      <feat name="tense" value="Pas"/>
      <feat name="type" value="PART"/>
   </struct>
   <struct type="VG" from="27889" to="27895">
      <feat name="voice" value="none"/>
      <feat name="tense" value="none"/>
      <feat name="type" value="MODAL"/>
   </struct>
</cesAna>